ies_tool/__init__.py
ies_tool/ies4-3.ttl
ies_tool/iesExtensions.ttl
ies_tool/ies_constants.py
ies_tool/ies_ontology.py
ies_tool/ies_plugin.py
ies_tool/ies_r4_3_0.shacl
ies_tool/ies_tool.py
ies_tool/rdflib_plugin.py
ies_tool/sparql_endpoint_plugin.py
ies_tool/utils.py
telicent_ies_tool-2.0.0.dist-info/licenses/LICENSE
telicent_ies_tool-2.0.0.dist-info/licenses/NOTICE
telicent_ies_tool-2.0.0.dist-info/METADATA
telicent_ies_tool-2.0.0.dist-info/WHEEL
telicent_ies_tool-2.0.0.dist-info/top_level.txt
telicent_ies_tool-2.0.0.dist-info/RECORD
