Metadata-Version: 2.4
Name: telicent-ies-tool
Version: 2.0.0
Summary: A library for working with the IES data standard
Author-email: Telicent Ltd <opensource@telicent.io>
License:                                  Apache License
Project-URL: Repository, https://github.com/telicent-oss/ies-tool
Project-URL: Changelog, https://github.com/telicent-oss/ies-tool/blob/main/CHANGELOG.md
Classifier: Development Status :: 4 - Beta
Classifier: Programming Language :: Python :: 3.10
Classifier: Programming Language :: Python :: 3.11
Classifier: Programming Language :: Python :: 3.12
Classifier: Programming Language :: Python :: 3 :: Only
Classifier: Topic :: Software Development
Classifier: Operating System :: Microsoft :: Windows
Classifier: Operating System :: POSIX
Classifier: Operating System :: Unix
Classifier: Operating System :: MacOS
Requires-Python: >=3.8
License-File: LICENSE
License-File: NOTICE
Requires-Dist: geohash-tools==0.2.0
Requires-Dist: python-geohash==0.8.5
Requires-Dist: pyshacl==0.25.0
Requires-Dist: requests==2.32.4
Requires-Dist: rdflib==6.3.2
Requires-Dist: phonenumbers==8.13.35
Requires-Dist: pycountry==24.6.1
Requires-Dist: validators==0.28.1
Requires-Dist: iso4217parse==0.5.1
Requires-Dist: shortuuid==1.0.13
Provides-Extra: dev
Requires-Dist: pre-commit==3.5.0; extra == "dev"
Requires-Dist: ruff==0.1.5; extra == "dev"
Requires-Dist: types-requests==2.31.0.10; extra == "dev"
Requires-Dist: mypy==1.7.0; extra == "dev"
Requires-Dist: mkdocs==1.5.3; extra == "dev"
Requires-Dist: mkdocs-material==9.5.11; extra == "dev"
Requires-Dist: mkdocstrings==0.24.0; extra == "dev"
Requires-Dist: mkdocstrings_python==1.8.0; extra == "dev"
Dynamic: license-file
